pyshdesings/__init__.py
pyshdesings-1.9.dist-info/METADATA
pyshdesings-1.9.dist-info/WHEEL
pyshdesings-1.9.dist-info/top_level.txt
pyshdesings-1.9.dist-info/RECORD
