Metadata-Version: 2.1
Name: pyshdesings
Version: 1.9
Summary: by billythegoat356, loTus01 and BlueRed
Author-email: <billythegoat356@gmail.com>
License: Eclipse Public License 2.0
Keywords: cli,fade,colors,terminal,tui
